repx/main.py
repx-0.0.1.dist-info/entry_points.txt
repx-0.0.1.dist-info/LICENSE
repx-0.0.1.dist-info/WHEEL
repx-0.0.1.dist-info/METADATA
repx-0.0.1.dist-info/RECORD
